Workbook

Sheet Assumptions
A1: Budget and cash flow 2026
A2: Pick a scenario in B4; the Model sheet follows it through INDEX/MATCH.
A4: Scenario | B4: Base
A5: Monthly growth | B5: =INDEX(Scenarios!$B$2:$B$4,MATCH($B$4,Scenarios!$A$2:$A$4,0)) -> 0.04
A6: Price per customer | B6: =INDEX(Scenarios!$C$2:$C$4,MATCH($B$4,Scenarios!$A$2:$A$4,0)) -> 49
A7: Monthly churn | B7: =INDEX(Scenarios!$D$2:$D$4,MATCH($B$4,Scenarios!$A$2:$A$4,0)) -> 0.02
A8: Marketing a month | B8: =_xlfn.XLOOKUP($B$4,Scenarios!$A$2:$A$4,Scenarios!$E$2:$E$4) -> 12000
A9: Customers in January | B9: 1200
A10: Cost to serve a customer | B10: 9
A11: Salaries a month | B11: 38000
A12: Opening cash | B12: 150000

Sheet Model
A1: Line | B1: Jan | C1: Feb | D1: Mar | E1: Apr | F1: May | G1: Jun | H1: Jul | I1: Aug | J1: Sep | K1: Oct | L1: Nov | M1: Dec | N1: Year
A2: Customers | B2: =Assumptions!$B$9 -> 1200 | C2: =ROUND(B2*(1+Assumptions!$B$5-Assumptions!$B$7),0) -> 1224 | D2: =ROUND(C2*(1+Assumptions!$B$5-Assumptions!$B$7),0) -> 1248 | E2: =ROUND(D2*(1+Assumptions!$B$5-Assumptions!$B$7),0) -> 1273 | F2: =ROUND(E2*(1+Assumptions!$B$5-Assumptions!$B$7),0) -> 1298 | G2: =ROUND(F2*(1+Assumptions!$B$5-Assumptions!$B$7),0) -> 1324 | H2: =ROUND(G2*(1+Assumptions!$B$5-Assumptions!$B$7),0) -> 1350 | I2: =ROUND(H2*(1+Assumptions!$B$5-Assumptions!$B$7),0) -> 1377 | J2: =ROUND(I2*(1+Assumptions!$B$5-Assumptions!$B$7),0) -> 1405 | ... M2: =ROUND(L2*(1+Assumptions!$B$5-Assumptions!$B$7),0) -> 1491 | N2: =M2 -> 1491
A3: Revenue | B3: =B2*Assumptions!$B$6 -> 58800 | C3: =C2*Assumptions!$B$6 -> 59976 | D3: =D2*Assumptions!$B$6 -> 61152 | E3: =E2*Assumptions!$B$6 -> 62377 | F3: =F2*Assumptions!$B$6 -> 63602 | G3: =G2*Assumptions!$B$6 -> 64876 | H3: =H2*Assumptions!$B$6 -> 66150 | I3: =I2*Assumptions!$B$6 -> 67473 | ... M3: =M2*Assumptions!$B$6 -> 73059 | N3: =SUM(B3:M3) -> 788165
A4: Cost to serve | B4: =-B2*Assumptions!$B$10 -> -10800 | C4: =-C2*Assumptions!$B$10 -> -11016 | D4: =-D2*Assumptions!$B$10 -> -11232 | E4: =-E2*Assumptions!$B$10 -> -11457 | F4: =-F2*Assumptions!$B$10 -> -11682 | G4: =-G2*Assumptions!$B$10 -> -11916 | H4: =-H2*Assumptions!$B$10 -> -12150 | I4: =-I2*Assumptions!$B$10 -> -12393 | ... M4: =-M2*Assumptions!$B$10 -> -13419 | N4: =SUM(B4:M4) -> -144765
A5: Marketing | B5: =-Assumptions!$B$8 -> -12000 | C5: =-Assumptions!$B$8 -> -12000 | D5: =-Assumptions!$B$8 -> -12000 | E5: =-Assumptions!$B$8 -> -12000 | F5: =-Assumptions!$B$8 -> -12000 | G5: =-Assumptions!$B$8 -> -12000 | H5: =-Assumptions!$B$8 -> -12000 | I5: =-Assumptions!$B$8 -> -12000 | ... M5: =-Assumptions!$B$8 -> -12000 | N5: =SUM(B5:M5) -> -144000
A6: Salaries | B6: =-Assumptions!$B$11 -> -38000 | C6: =-Assumptions!$B$11 -> -38000 | D6: =-Assumptions!$B$11 -> -38000 | E6: =-Assumptions!$B$11 -> -38000 | F6: =-Assumptions!$B$11 -> -38000 | G6: =-Assumptions!$B$11 -> -38000 | H6: =-Assumptions!$B$11 -> -38000 | I6: =-Assumptions!$B$11 -> -38000 | ... M6: =-Assumptions!$B$11 -> -38000 | N6: =SUM(B6:M6) -> -456000
A7: Net | B7: =SUM(B3:B6) -> -2000 | C7: =SUM(C3:C6) -> -1040 | D7: =SUM(D3:D6) -> -80 | E7: =SUM(E3:E6) -> 920 | F7: =SUM(F3:F6) -> 1920 | G7: =SUM(G3:G6) -> 2960 | H7: =SUM(H3:H6) -> 4000 | I7: =SUM(I3:I6) -> 5080 | ... M7: =SUM(M3:M6) -> 9640 | N7: =SUM(B7:M7) -> 43400
A8: Cash at month end | B8: =Assumptions!$B$12+B7 -> 148000 | C8: =B8+C7 -> 146960 | D8: =C8+D7 -> 146880 | E8: =D8+E7 -> 147800 | F8: =E8+F7 -> 149720 | G8: =F8+G7 -> 152680 | H8: =G8+H7 -> 156680 | I8: =H8+I7 -> 161760 | J8: =I8+J7 -> 167960 | ... M8: =L8+M7 -> 193400 | N8: =M8 -> 193400
A11: Month | B11: Revenue | C11: Costs | D11: Net | E11: Cash | G11: Customers | H11: Revenue | J11: Month | K11: Cash
A12: Jan | B12: =B3 -> 58800 | C12: =-(B4+B5+B6) -> 60800 | D12: =B7 -> -2000 | E12: =B8 -> 148000 | G12: =B2 -> 1200 | H12: =B3 -> 58800 | J12: =A12 -> Jan | K12: =E12 -> 148000
A13: Feb | B13: =C3 -> 59976 | C13: =-(C4+C5+C6) -> 61016 | D13: =C7 -> -1040 | E13: =C8 -> 146960 | G13: =C2 -> 1224 | H13: =C3 -> 59976 | J13: =A13 -> Feb | K13: =E13 -> 146960
A14: Mar | B14: =D3 -> 61152 | C14: =-(D4+D5+D6) -> 61232 | D14: =D7 -> -80 | E14: =D8 -> 146880 | G14: =D2 -> 1248 | H14: =D3 -> 61152 | J14: =A14 -> Mar | K14: =E14 -> 146880
A15: Apr | B15: =E3 -> 62377 | C15: =-(E4+E5+E6) -> 61457 | D15: =E7 -> 920 | E15: =E8 -> 147800 | G15: =E2 -> 1273 | H15: =E3 -> 62377 | J15: =A15 -> Apr | K15: =E15 -> 147800
A16: May | B16: =F3 -> 63602 | C16: =-(F4+F5+F6) -> 61682 | D16: =F7 -> 1920 | E16: =F8 -> 149720 | G16: =F2 -> 1298 | H16: =F3 -> 63602 | J16: =A16 -> May | K16: =E16 -> 149720
A17: Jun | B17: =G3 -> 64876 | C17: =-(G4+G5+G6) -> 61916 | D17: =G7 -> 2960 | E17: =G8 -> 152680 | G17: =G2 -> 1324 | H17: =G3 -> 64876 | J17: =A17 -> Jun | K17: =E17 -> 152680
A18: Jul | B18: =H3 -> 66150 | C18: =-(H4+H5+H6) -> 62150 | D18: =H7 -> 4000 | E18: =H8 -> 156680 | G18: =H2 -> 1350 | H18: =H3 -> 66150 | J18: =A18 -> Jul | K18: =E18 -> 156680
A19: Aug | B19: =I3 -> 67473 | C19: =-(I4+I5+I6) -> 62393 | D19: =I7 -> 5080 | E19: =I8 -> 161760 | G19: =I2 -> 1377 | H19: =I3 -> 67473 | J19: =A19 -> Aug | K19: =E19 -> 161760
A20: Sep | B20: =J3 -> 68845 | C20: =-(J4+J5+J6) -> 62645 | D20: =J7 -> 6200 | E20: =J8 -> 167960 | G20: =J2 -> 1405 | H20: =J3 -> 68845 | J20: =A20 -> Sep | K20: =E20 -> 167960
A21: Oct | B21: =K3 -> 70217 | C21: =-(K4+K5+K6) -> 62897 | D21: =K7 -> 7320 | E21: =K8 -> 175280 | G21: =K2 -> 1433 | H21: =K3 -> 70217 | J21: =A21 -> Oct | K21: =E21 -> 175280
A22: Nov | B22: =L3 -> 71638 | C22: =-(L4+L5+L6) -> 63158 | D22: =L7 -> 8480 | E22: =L8 -> 183760 | G22: =L2 -> 1462 | H22: =L3 -> 71638 | J22: =A22 -> Nov | K22: =E22 -> 183760
A23: Dec | B23: =M3 -> 73059 | C23: =-(M4+M5+M6) -> 63419 | D23: =M7 -> 9640 | E23: =M8 -> 193400 | G23: =M2 -> 1491 | H23: =M3 -> 73059 | J23: =A23 -> Dec | K23: =E23 -> 193400

Sheet Scenarios
A1: Scenario | B1: Monthly growth | C1: Price | D1: Churn | E1: Marketing
A2: Base | B2: 0.04 | C2: 49 | D2: 0.02 | E2: 12000
A3: Best | B3: 0.07 | C3: 55 | D3: 0.015 | E3: 15000
A4: Worst | B4: 0.01 | C4: 45 | D4: 0.035 | E4: 9000
