Workbook

Sheet Dashboard
A1: Sales performance 2026
A2: Every figure is a formula over the Orders sheet: change an order and the dashboard follows.
A4: Revenue | B4: Gross margin | C4: Orders | D4: Average order | E4: Returned
A5: =SUMIFS(Orders!I:I,Orders!L:L,"<>Returned") -> 448677 | B5: =IFERROR(1-SUMIFS(Orders!J:J,Orders!L:L,"<>Returned")/A5,0) -> 0.57700306 | C5: =COUNTIFS(Orders!A:A,"SO-*",Orders!L:L,"<>Returned") -> 228 | D5: =IFERROR(A5/C5,0) -> 1967.8816 | E5: =COUNTIFS(Orders!L:L,"Returned") -> 12
A8: Month | B8: North | C8: South | D8: East | E8: West | G8: Category | H8: Revenue | J8: Leaderboard | K8: Sold
A9: =DATE(2026,1,1) -> 46023 | B9: =SUMIFS(Orders!$I:$I,Orders!$C:$C,B$8,Orders!$B:$B,">="&$A9,Orders!$B:$B,"<"&EDATE($A9,1)) -> 21597 | C9: =SUMIFS(Orders!$I:$I,Orders!$C:$C,C$8,Orders!$B:$B,">="&$A9,Orders!$B:$B,"<"&EDATE($A9,1)) -> 4500 | D9: =SUMIFS(Orders!$I:$I,Orders!$C:$C,D$8,Orders!$B:$B,">="&$A9,Orders!$B:$B,"<"&EDATE($A9,1)) -> 7679 | E9: =SUMIFS(Orders!$I:$I,Orders!$C:$C,E$8,Orders!$B:$B,">="&$A9,Orders!$B:$B,"<"&EDATE($A9,1)) -> 14487 | G9: Hardware | H9: =SUMIFS(Orders!$I:$I,Orders!$G:$G,G9) -> 245539 | J9: {=_xlfn.SORTBY(Reps!A2:A7,Reps!D2:D7,-1)} -> Asha Rao | K9: {=_xlfn.SORTBY(Reps!D2:D7,Reps!D2:D7,-1)} -> 93973
A10: =DATE(2026,2,1) -> 46054 | B10: =SUMIFS(Orders!$I:$I,Orders!$C:$C,B$8,Orders!$B:$B,">="&$A10,Orders!$B:$B,"<"&EDATE($A10,1)) -> 8677 | C10: =SUMIFS(Orders!$I:$I,Orders!$C:$C,C$8,Orders!$B:$B,">="&$A10,Orders!$B:$B,"<"&EDATE($A10,1)) -> 19782 | D10: =SUMIFS(Orders!$I:$I,Orders!$C:$C,D$8,Orders!$B:$B,">="&$A10,Orders!$B:$B,"<"&EDATE($A10,1)) -> 0 | E10: =SUMIFS(Orders!$I:$I,Orders!$C:$C,E$8,Orders!$B:$B,">="&$A10,Orders!$B:$B,"<"&EDATE($A10,1)) -> 11692 | G10: Software | H10: =SUMIFS(Orders!$I:$I,Orders!$G:$G,G10) -> 103505 | J10: Ben Okafor | K10: 81362
A11: =DATE(2026,3,1) -> 46082 | B11: =SUMIFS(Orders!$I:$I,Orders!$C:$C,B$8,Orders!$B:$B,">="&$A11,Orders!$B:$B,"<"&EDATE($A11,1)) -> 15212 | C11: =SUMIFS(Orders!$I:$I,Orders!$C:$C,C$8,Orders!$B:$B,">="&$A11,Orders!$B:$B,"<"&EDATE($A11,1)) -> 900 | D11: =SUMIFS(Orders!$I:$I,Orders!$C:$C,D$8,Orders!$B:$B,">="&$A11,Orders!$B:$B,"<"&EDATE($A11,1)) -> 3600 | E11: =SUMIFS(Orders!$I:$I,Orders!$C:$C,E$8,Orders!$B:$B,">="&$A11,Orders!$B:$B,"<"&EDATE($A11,1)) -> 14983 | G11: Services | H11: =SUMIFS(Orders!$I:$I,Orders!$G:$G,G11) -> 123300 | J11: Farid Haddad | K11: 77985
A12: =DATE(2026,4,1) -> 46113 | B12: =SUMIFS(Orders!$I:$I,Orders!$C:$C,B$8,Orders!$B:$B,">="&$A12,Orders!$B:$B,"<"&EDATE($A12,1)) -> 13152 | C12: =SUMIFS(Orders!$I:$I,Orders!$C:$C,C$8,Orders!$B:$B,">="&$A12,Orders!$B:$B,"<"&EDATE($A12,1)) -> 8663 | D12: =SUMIFS(Orders!$I:$I,Orders!$C:$C,D$8,Orders!$B:$B,">="&$A12,Orders!$B:$B,"<"&EDATE($A12,1)) -> 11443 | E12: =SUMIFS(Orders!$I:$I,Orders!$C:$C,E$8,Orders!$B:$B,">="&$A12,Orders!$B:$B,"<"&EDATE($A12,1)) -> 6690 | J12: Dara Kim | K12: 75889
A13: =DATE(2026,5,1) -> 46143 | B13: =SUMIFS(Orders!$I:$I,Orders!$C:$C,B$8,Orders!$B:$B,">="&$A13,Orders!$B:$B,"<"&EDATE($A13,1)) -> 14139 | C13: =SUMIFS(Orders!$I:$I,Orders!$C:$C,C$8,Orders!$B:$B,">="&$A13,Orders!$B:$B,"<"&EDATE($A13,1)) -> 2400 | D13: =SUMIFS(Orders!$I:$I,Orders!$C:$C,D$8,Orders!$B:$B,">="&$A13,Orders!$B:$B,"<"&EDATE($A13,1)) -> 9203 | E13: =SUMIFS(Orders!$I:$I,Orders!$C:$C,E$8,Orders!$B:$B,">="&$A13,Orders!$B:$B,"<"&EDATE($A13,1)) -> 10559 | J13: Chen Wei | K13: 73015
A14: =DATE(2026,6,1) -> 46174 | B14: =SUMIFS(Orders!$I:$I,Orders!$C:$C,B$8,Orders!$B:$B,">="&$A14,Orders!$B:$B,"<"&EDATE($A14,1)) -> 7179 | C14: =SUMIFS(Orders!$I:$I,Orders!$C:$C,C$8,Orders!$B:$B,">="&$A14,Orders!$B:$B,"<"&EDATE($A14,1)) -> 6080 | D14: =SUMIFS(Orders!$I:$I,Orders!$C:$C,D$8,Orders!$B:$B,">="&$A14,Orders!$B:$B,"<"&EDATE($A14,1)) -> 7114 | E14: =SUMIFS(Orders!$I:$I,Orders!$C:$C,E$8,Orders!$B:$B,">="&$A14,Orders!$B:$B,"<"&EDATE($A14,1)) -> 11444 | G14: Best product | H14: =INDEX(Products!B2:B8,MATCH(MAX(Products!G2:G8),Products!G2:G8,0)) -> Gadget | J14: Elena Ruiz | K14: 70120
A15: =DATE(2026,7,1) -> 46204 | B15: =SUMIFS(Orders!$I:$I,Orders!$C:$C,B$8,Orders!$B:$B,">="&$A15,Orders!$B:$B,"<"&EDATE($A15,1)) -> 18896 | C15: =SUMIFS(Orders!$I:$I,Orders!$C:$C,C$8,Orders!$B:$B,">="&$A15,Orders!$B:$B,"<"&EDATE($A15,1)) -> 6705 | D15: =SUMIFS(Orders!$I:$I,Orders!$C:$C,D$8,Orders!$B:$B,">="&$A15,Orders!$B:$B,"<"&EDATE($A15,1)) -> 3741 | E15: =SUMIFS(Orders!$I:$I,Orders!$C:$C,E$8,Orders!$B:$B,">="&$A15,Orders!$B:$B,"<"&EDATE($A15,1)) -> 6204
A16: =DATE(2026,8,1) -> 46235 | B16: =SUMIFS(Orders!$I:$I,Orders!$C:$C,B$8,Orders!$B:$B,">="&$A16,Orders!$B:$B,"<"&EDATE($A16,1)) -> 11972 | C16: =SUMIFS(Orders!$I:$I,Orders!$C:$C,C$8,Orders!$B:$B,">="&$A16,Orders!$B:$B,"<"&EDATE($A16,1)) -> 15471 | D16: =SUMIFS(Orders!$I:$I,Orders!$C:$C,D$8,Orders!$B:$B,">="&$A16,Orders!$B:$B,"<"&EDATE($A16,1)) -> 0 | E16: =SUMIFS(Orders!$I:$I,Orders!$C:$C,E$8,Orders!$B:$B,">="&$A16,Orders!$B:$B,"<"&EDATE($A16,1)) -> 17016
A17: =DATE(2026,9,1) -> 46266 | B17: =SUMIFS(Orders!$I:$I,Orders!$C:$C,B$8,Orders!$B:$B,">="&$A17,Orders!$B:$B,"<"&EDATE($A17,1)) -> 10902 | C17: =SUMIFS(Orders!$I:$I,Orders!$C:$C,C$8,Orders!$B:$B,">="&$A17,Orders!$B:$B,"<"&EDATE($A17,1)) -> 2832 | D17: =SUMIFS(Orders!$I:$I,Orders!$C:$C,D$8,Orders!$B:$B,">="&$A17,Orders!$B:$B,"<"&EDATE($A17,1)) -> 11226 | E17: =SUMIFS(Orders!$I:$I,Orders!$C:$C,E$8,Orders!$B:$B,">="&$A17,Orders!$B:$B,"<"&EDATE($A17,1)) -> 15905 | J17: Open orders over $3,000
A18: =DATE(2026,10,1) -> 46296 | B18: =SUMIFS(Orders!$I:$I,Orders!$C:$C,B$8,Orders!$B:$B,">="&$A18,Orders!$B:$B,"<"&EDATE($A18,1)) -> 14037 | C18: =SUMIFS(Orders!$I:$I,Orders!$C:$C,C$8,Orders!$B:$B,">="&$A18,Orders!$B:$B,"<"&EDATE($A18,1)) -> 3938 | D18: =SUMIFS(Orders!$I:$I,Orders!$C:$C,D$8,Orders!$B:$B,">="&$A18,Orders!$B:$B,"<"&EDATE($A18,1)) -> 4371 | E18: =SUMIFS(Orders!$I:$I,Orders!$C:$C,E$8,Orders!$B:$B,">="&$A18,Orders!$B:$B,"<"&EDATE($A18,1)) -> 19347 | J18: {=_xlfn._xlws.FILTER(Orders!A2:A241,(Orders!L2:L241="Open")*(Orders!I2:I241>3000),"None")} -> SO-10089
A19: =DATE(2026,11,1) -> 46327 | B19: =SUMIFS(Orders!$I:$I,Orders!$C:$C,B$8,Orders!$B:$B,">="&$A19,Orders!$B:$B,"<"&EDATE($A19,1)) -> 11595 | C19: =SUMIFS(Orders!$I:$I,Orders!$C:$C,C$8,Orders!$B:$B,">="&$A19,Orders!$B:$B,"<"&EDATE($A19,1)) -> 605 | D19: =SUMIFS(Orders!$I:$I,Orders!$C:$C,D$8,Orders!$B:$B,">="&$A19,Orders!$B:$B,"<"&EDATE($A19,1)) -> 8225 | E19: =SUMIFS(Orders!$I:$I,Orders!$C:$C,E$8,Orders!$B:$B,">="&$A19,Orders!$B:$B,"<"&EDATE($A19,1)) -> 13375 | J19: SO-10098
A20: =DATE(2026,12,1) -> 46357 | B20: =SUMIFS(Orders!$I:$I,Orders!$C:$C,B$8,Orders!$B:$B,">="&$A20,Orders!$B:$B,"<"&EDATE($A20,1)) -> 16735 | C20: =SUMIFS(Orders!$I:$I,Orders!$C:$C,C$8,Orders!$B:$B,">="&$A20,Orders!$B:$B,"<"&EDATE($A20,1)) -> 9486 | D20: =SUMIFS(Orders!$I:$I,Orders!$C:$C,D$8,Orders!$B:$B,">="&$A20,Orders!$B:$B,"<"&EDATE($A20,1)) -> 6413 | E20: =SUMIFS(Orders!$I:$I,Orders!$C:$C,E$8,Orders!$B:$B,">="&$A20,Orders!$B:$B,"<"&EDATE($A20,1)) -> 12172 | J20: SO-10117
J21: SO-10131
J22: SO-10150
J23: SO-10153
J24: SO-10163
J25: SO-10170
J26: SO-10187
J27: SO-10198
J28: SO-10206
J29: SO-10219
J30: SO-10222

Sheet Orders
A1: Order | B1: Date | C1: Region | D1: Rep | E1: SKU | F1: Product | G1: Category | H1: Qty | I1: Revenue | J1: Cost | K1: Margin | L1: Status
A2: SO-10001 | B2: 46024 | C2: North | D2: Asha Rao | E2: P-100 | F2: =_xlfn.XLOOKUP(E2,Products!$A:$A,Products!$B:$B,"?") -> Widget | G2: =_xlfn.XLOOKUP(E2,Products!$A:$A,Products!$C:$C,"?") -> Hardware | H2: 58 | I2: =H2*_xlfn.XLOOKUP(E2,Products!$A:$A,Products!$D:$D,0) -> 1392 | J2: =H2*_xlfn.XLOOKUP(E2,Products!$A:$A,Products!$E:$E,0) -> 638 | K2: =IFERROR((I2-J2)/I2,0) -> 0.54166667 | L2: Paid
A3: SO-10002 | B3: 46027 | C3: West | D3: Dara Kim | E3: P-400 | F3: =_xlfn.XLOOKUP(E3,Products!$A:$A,Products!$B:$B,"?") -> Setup | G3: =_xlfn.XLOOKUP(E3,Products!$A:$A,Products!$C:$C,"?") -> Services | H3: 3 | I3: =H3*_xlfn.XLOOKUP(E3,Products!$A:$A,Products!$D:$D,0) -> 1350 | J3: =H3*_xlfn.XLOOKUP(E3,Products!$A:$A,Products!$E:$E,0) -> 780 | K3: =IFERROR((I3-J3)/I3,0) -> 0.42222222 | L3: Returned
A4: SO-10003 | B4: 46030 | C4: South | D4: Ben Okafor | E4: P-400 | F4: =_xlfn.XLOOKUP(E4,Products!$A:$A,Products!$B:$B,"?") -> Setup | G4: =_xlfn.XLOOKUP(E4,Products!$A:$A,Products!$C:$C,"?") -> Services | H4: 2 | I4: =H4*_xlfn.XLOOKUP(E4,Products!$A:$A,Products!$D:$D,0) -> 900 | J4: =H4*_xlfn.XLOOKUP(E4,Products!$A:$A,Products!$E:$E,0) -> 520 | K4: =IFERROR((I4-J4)/I4,0) -> 0.42222222 | L4: Paid
A5: SO-10004 | B5: 46030 | C5: North | D5: Asha Rao | E5: P-200 | F5: =_xlfn.XLOOKUP(E5,Products!$A:$A,Products!$B:$B,"?") -> Gadget | G5: =_xlfn.XLOOKUP(E5,Products!$A:$A,Products!$C:$C,"?") -> Hardware | H5: 58 | I5: =H5*_xlfn.XLOOKUP(E5,Products!$A:$A,Products!$D:$D,0) -> 5162 | J5: =H5*_xlfn.XLOOKUP(E5,Products!$A:$A,Products!$E:$E,0) -> 2726 | K5: =IFERROR((I5-J5)/I5,0) -> 0.47191011 | L5: Paid
A6: SO-10005 | B6: 46033 | C6: West | D6: Dara Kim | E6: P-410 | F6: =_xlfn.XLOOKUP(E6,Products!$A:$A,Products!$B:$B,"?") -> Training day | G6: =_xlfn.XLOOKUP(E6,Products!$A:$A,Products!$C:$C,"?") -> Services | H6: 1 | I6: =H6*_xlfn.XLOOKUP(E6,Products!$A:$A,Products!$D:$D,0) -> 1200 | J6: =H6*_xlfn.XLOOKUP(E6,Products!$A:$A,Products!$E:$E,0) -> 640 | K6: =IFERROR((I6-J6)/I6,0) -> 0.46666667 | L6: Open
A7: SO-10006 | B7: 46031 | C7: North | D7: Elena Ruiz | E7: P-400 | F7: =_xlfn.XLOOKUP(E7,Products!$A:$A,Products!$B:$B,"?") -> Setup | G7: =_xlfn.XLOOKUP(E7,Products!$A:$A,Products!$C:$C,"?") -> Services | H7: 1 | I7: =H7*_xlfn.XLOOKUP(E7,Products!$A:$A,Products!$D:$D,0) -> 450 | J7: =H7*_xlfn.XLOOKUP(E7,Products!$A:$A,Products!$E:$E,0) -> 260 | K7: =IFERROR((I7-J7)/I7,0) -> 0.42222222 | L7: Open
A8: SO-10007 | B8: 46037 | C8: North | D8: Asha Rao | E8: P-100 | F8: =_xlfn.XLOOKUP(E8,Products!$A:$A,Products!$B:$B,"?") -> Widget | G8: =_xlfn.XLOOKUP(E8,Products!$A:$A,Products!$C:$C,"?") -> Hardware | H8: 23 | I8: =H8*_xlfn.XLOOKUP(E8,Products!$A:$A,Products!$D:$D,0) -> 552 | J8: =H8*_xlfn.XLOOKUP(E8,Products!$A:$A,Products!$E:$E,0) -> 253 | K8: =IFERROR((I8-J8)/I8,0) -> 0.54166667 | L8: Paid
A9: SO-10008 | B9: 46034 | C9: East | D9: Chen Wei | E9: P-200 | F9: =_xlfn.XLOOKUP(E9,Products!$A:$A,Products!$B:$B,"?") -> Gadget | G9: =_xlfn.XLOOKUP(E9,Products!$A:$A,Products!$C:$C,"?") -> Hardware | H9: 56 | I9: =H9*_xlfn.XLOOKUP(E9,Products!$A:$A,Products!$D:$D,0) -> 4984 | J9: =H9*_xlfn.XLOOKUP(E9,Products!$A:$A,Products!$E:$E,0) -> 2632 | K9: =IFERROR((I9-J9)/I9,0) -> 0.47191011 | L9: Paid
A10: SO-10009 | B10: 46047 | C10: West | D10: Dara Kim | E10: P-400 | F10: =_xlfn.XLOOKUP(E10,Products!$A:$A,Products!$B:$B,"?") -> Setup | G10: =_xlfn.XLOOKUP(E10,Products!$A:$A,Products!$C:$C,"?") -> Services | H10: 3 | I10: =H10*_xlfn.XLOOKUP(E10,Products!$A:$A,Products!$D:$D,0) -> 1350 | J10: =H10*_xlfn.XLOOKUP(E10,Products!$A:$A,Products!$E:$E,0) -> 780 | K10: =IFERROR((I10-J10)/I10,0) -> 0.42222222 | L10: Open
A11: SO-10010 | B11: 46039 | C11: North | D11: Asha Rao | E11: P-100 | F11: =_xlfn.XLOOKUP(E11,Products!$A:$A,Products!$B:$B,"?") -> Widget | G11: =_xlfn.XLOOKUP(E11,Products!$A:$A,Products!$C:$C,"?") -> Hardware | H11: 73 | I11: =H11*_xlfn.XLOOKUP(E11,Products!$A:$A,Products!$D:$D,0) -> 1752 | J11: =H11*_xlfn.XLOOKUP(E11,Products!$A:$A,Products!$E:$E,0) -> 803 | K11: =IFERROR((I11-J11)/I11,0) -> 0.54166667 | L11: Paid
A12: SO-10011 | B12: 46043 | C12: West | D12: Dara Kim | E12: P-410 | F12: =_xlfn.XLOOKUP(E12,Products!$A:$A,Products!$B:$B,"?") -> Training day | G12: =_xlfn.XLOOKUP(E12,Products!$A:$A,Products!$C:$C,"?") -> Services | H12: 1 | I12: =H12*_xlfn.XLOOKUP(E12,Products!$A:$A,Products!$D:$D,0) -> 1200 | J12: =H12*_xlfn.XLOOKUP(E12,Products!$A:$A,Products!$E:$E,0) -> 640 | K12: =IFERROR((I12-J12)/I12,0) -> 0.46666667 | L12: Open
A13: SO-10012 | B13: 46034 | C13: West | D13: Farid Haddad | E13: P-310 | F13: =_xlfn.XLOOKUP(E13,Products!$A:$A,Products!$B:$B,"?") -> Cloud Seat Plus | G13: =_xlfn.XLOOKUP(E13,Products!$A:$A,Products!$C:$C,"?") -> Software | H13: 28 | I13: =H13*_xlfn.XLOOKUP(E13,Products!$A:$A,Products!$D:$D,0) -> 1540 | J13: =H13*_xlfn.XLOOKUP(E13,Products!$A:$A,Products!$E:$E,0) -> 196 | K13: =IFERROR((I13-J13)/I13,0) -> 0.87272727 | L13: Paid
... A241: SO-10240 | B241: 46365 | C241: North | D241: Elena Ruiz | E241: P-200 | F241: =_xlfn.XLOOKUP(E241,Products!$A:$A,Products!$B:$B,"?") -> Gadget | G241: =_xlfn.XLOOKUP(E241,Products!$A:$A,Products!$C:$C,"?") -> Hardware | H241: 73 | I241: =H241*_xlfn.XLOOKUP(E241,Products!$A:$A,Products!$D:$D,0) -> 6497 | J241: =H241*_xlfn.XLOOKUP(E241,Products!$A:$A,Products!$E:$E,0) -> 3431 | K241: =IFERROR((I241-J241)/I241,0) -> 0.47191011 | L241: Paid

Sheet Products
A1: SKU | B1: Product | C1: Category | D1: Unit price | E1: Unit cost | F1: Margin | G1: Revenue
A2: P-100 | B2: Widget | C2: Hardware | D2: 24 | E2: 11 | F2: =(D2-E2)/D2 -> 0.54166667 | G2: =SUMIFS(Orders!$I:$I,Orders!$E:$E,A2) -> 45696
A3: P-110 | B3: Widget Pro | C3: Hardware | D3: 49 | E3: 22 | F3: =(D3-E3)/D3 -> 0.55102041 | G3: =SUMIFS(Orders!$I:$I,Orders!$E:$E,A3) -> 76489
A4: P-200 | B4: Gadget | C4: Hardware | D4: 89 | E4: 47 | F4: =(D4-E4)/D4 -> 0.47191011 | G4: =SUMIFS(Orders!$I:$I,Orders!$E:$E,A4) -> 123354
A5: P-300 | B5: Cloud Seat | C5: Software | D5: 30 | E5: 4 | F5: =(D5-E5)/D5 -> 0.86666667 | G5: =SUMIFS(Orders!$I:$I,Orders!$E:$E,A5) -> 25680
A6: P-310 | B6: Cloud Seat Plus | C6: Software | D6: 55 | E6: 7 | F6: =(D6-E6)/D6 -> 0.87272727 | G6: =SUMIFS(Orders!$I:$I,Orders!$E:$E,A6) -> 77825
A7: P-400 | B7: Setup | C7: Services | D7: 450 | E7: 260 | F7: =(D7-E7)/D7 -> 0.42222222 | G7: =SUMIFS(Orders!$I:$I,Orders!$E:$E,A7) -> 40500
A8: P-410 | B8: Training day | C8: Services | D8: 1200 | E8: 640 | F8: =(D8-E8)/D8 -> 0.46666667 | G8: =SUMIFS(Orders!$I:$I,Orders!$E:$E,A8) -> 82800

Sheet Reps
A1: Rep | B1: Region | C1: Annual target | D1: Sold | E1: Attainment | F1: Orders | H1: Rep | I1: Sold | J1: Target
A2: Asha Rao | B2: North | C2: 180000 | D2: =SUMIFS(Orders!$I:$I,Orders!$D:$D,A2) -> 93973 | E2: =IFERROR(D2/C2,0) -> 0.52207222 | F2: =COUNTIFS(Orders!$D:$D,A2) -> 52 | H2: =A2 -> Asha Rao | I2: =D2 -> 93973 | J2: =C2 -> 180000
A3: Ben Okafor | B3: South | C3: 150000 | D3: =SUMIFS(Orders!$I:$I,Orders!$D:$D,A3) -> 81362 | E3: =IFERROR(D3/C3,0) -> 0.54241333 | F3: =COUNTIFS(Orders!$D:$D,A3) -> 40 | H3: =A3 -> Ben Okafor | I3: =D3 -> 81362 | J3: =C3 -> 150000
A4: Chen Wei | B4: East | C4: 170000 | D4: =SUMIFS(Orders!$I:$I,Orders!$D:$D,A4) -> 73015 | E4: =IFERROR(D4/C4,0) -> 0.4295 | F4: =COUNTIFS(Orders!$D:$D,A4) -> 34 | H4: =A4 -> Chen Wei | I4: =D4 -> 73015 | J4: =C4 -> 170000
A5: Dara Kim | B5: West | C5: 160000 | D5: =SUMIFS(Orders!$I:$I,Orders!$D:$D,A5) -> 75889 | E5: =IFERROR(D5/C5,0) -> 0.47430625 | F5: =COUNTIFS(Orders!$D:$D,A5) -> 38 | H5: =A5 -> Dara Kim | I5: =D5 -> 75889 | J5: =C5 -> 160000
A6: Elena Ruiz | B6: North | C6: 140000 | D6: =SUMIFS(Orders!$I:$I,Orders!$D:$D,A6) -> 70120 | E6: =IFERROR(D6/C6,0) -> 0.50085714 | F6: =COUNTIFS(Orders!$D:$D,A6) -> 39 | H6: =A6 -> Elena Ruiz | I6: =D6 -> 70120 | J6: =C6 -> 140000
A7: Farid Haddad | B7: West | C7: 155000 | D7: =SUMIFS(Orders!$I:$I,Orders!$D:$D,A7) -> 77985 | E7: =IFERROR(D7/C7,0) -> 0.50312903 | F7: =COUNTIFS(Orders!$D:$D,A7) -> 37 | H7: =A7 -> Farid Haddad | I7: =D7 -> 77985 | J7: =C7 -> 155000
